{
	"name": "Demo_Start",
	"layers": [
		{
			"name": "Terrain",
			"overriden": 0,
			"instances": [
				{
					"type": "Tiles_Dungeon",
					"properties": {
						"initially-visible": true,
						"tile-width": 20,
						"tile-height": 20,
						"tile-x-offset": 0,
						"tile-y-offset": 0,
						"tile-x-spacing": 0,
						"tile-y-spacing": 0,
						"tile-x-drawing-offset": 0,
						"tile-y-drawing-offset": 0,
						"drawing-mode": "top-to-right"
					},
					"uid": 223,
					"instanceVariables": {},
					"behaviors": {},
					"ownData": {
						"tilemapData": {
							"width": 19,
							"height": 14,
							"max-width": 23,
							"max-height": 17,
							"data": "6x0,10,26,10x0,34,2x42,48,7x42,50,5x0,35,10,8x18,26,51,5x0,35,11,8x19,27,51,5x0,35,11,8x19,27,51,5x0,16,11,8x19,27,51,5x0,35,11,8x19,27,39,5x0,56,11,8x19,27,51,4x0,10,18,31,8x19,27,40,42,3x0,11,10x19,23,17,25,3x0,12,20,30,8x19,27,38,44,4x0,54,11,8x19,27,51,5x0,35,11,8x19,27,51,5x0,16,11,8x19,27,51,5x0,35,11,8x19,27,51,5x0,35,11,8x19,27,51,5x0,35,12,8x20,28,51,5x0,36,10x44,52,5x0,12x42,72x0"
						},
						"tile-width": 20,
						"tile-height": 20,
						"tile-x-offset": 0,
						"tile-y-offset": 0,
						"tile-x-spacing": 0,
						"tile-y-spacing": 0
					},
					"world": {
						"x": -20,
						"y": -20,
						"width": 380,
						"height": 280,
						"originX": 0,
						"originY": 0,
						"color": [
							1,
							1,
							1,
							1
						],
						"zElevation": 0
					}
				},
				{
					"type": "SmallTiles_Dungeon",
					"properties": {
						"initially-visible": true,
						"tile-width": 10,
						"tile-height": 10,
						"tile-x-offset": 0,
						"tile-y-offset": 0,
						"tile-x-spacing": 0,
						"tile-y-spacing": 0,
						"tile-x-drawing-offset": 0,
						"tile-y-drawing-offset": 0,
						"drawing-mode": "top-to-right"
					},
					"uid": 224,
					"instanceVariables": {},
					"behaviors": {},
					"ownData": {
						"tilemapData": {
							"width": 4,
							"height": 4,
							"max-width": 34,
							"max-height": 27,
							"data": "57x0,277,26x0,278,833x0"
						},
						"tile-width": 10,
						"tile-height": 10,
						"tile-x-offset": 0,
						"tile-y-offset": 0,
						"tile-x-spacing": 0,
						"tile-y-spacing": 0
					},
					"world": {
						"x": 340,
						"y": -40,
						"width": 40,
						"height": 40,
						"originX": 0,
						"originY": 0,
						"color": [
							1,
							1,
							1,
							1
						],
						"zElevation": 0
					}
				},
				{
					"type": "SmallTiles_Dungeon",
					"properties": {
						"initially-visible": true,
						"tile-width": 10,
						"tile-height": 10,
						"tile-x-offset": 0,
						"tile-y-offset": 0,
						"tile-x-spacing": 0,
						"tile-y-spacing": 0,
						"tile-x-drawing-offset": 0,
						"tile-y-drawing-offset": 0,
						"drawing-mode": "top-to-right"
					},
					"uid": 36,
					"instanceVariables": {},
					"behaviors": {},
					"ownData": {
						"tilemapData": {
							"width": 6,
							"height": 4,
							"max-width": 36,
							"max-height": 27,
							"data": "84x0,92,887x0"
						},
						"tile-width": 10,
						"tile-height": 10,
						"tile-x-offset": 0,
						"tile-y-offset": 0,
						"tile-x-spacing": 0,
						"tile-y-spacing": 0
					},
					"world": {
						"x": 140,
						"y": 180,
						"width": 60,
						"height": 40,
						"originX": 0,
						"originY": 0,
						"color": [
							1,
							1,
							1,
							1
						],
						"zElevation": 0
					}
				},
				{
					"type": "SkillPickup",
					"properties": {
						"initially-visible": true,
						"initial-animation": "shield",
						"initial-frame": 0,
						"enable-collisions": true,
						"live-preview": false
					},
					"uid": 61,
					"instanceVariables": {
						"CurrentSkill": "shield",
						"Selected": false
					},
					"behaviors": {
						"Persist": {
							"properties": {}
						}
					},
					"world": {
						"x": 160,
						"y": 120,
						"width": 18,
						"height": 18,
						"originX": -0.05555555555555555,
						"originY": -0.05555555555555555,
						"color": [
							1,
							1,
							1,
							1
						],
						"angle": 0,
						"zElevation": 0
					}
				},
				{
					"type": "Dungeon_Torch",
					"properties": {
						"initially-visible": true,
						"initial-animation": "Animation 1",
						"initial-frame": 0,
						"enable-collisions": true,
						"live-preview": false
					},
					"uid": 91,
					"instanceVariables": {},
					"behaviors": {},
					"world": {
						"x": 80,
						"y": 0,
						"width": 20,
						"height": 20,
						"originX": 0,
						"originY": 0,
						"color": [
							1,
							1,
							1,
							1
						],
						"angle": 0,
						"zElevation": 0
					}
				},
				{
					"type": "Dungeon_Torch",
					"properties": {
						"initially-visible": true,
						"initial-animation": "Animation 1",
						"initial-frame": 0,
						"enable-collisions": true,
						"live-preview": false
					},
					"uid": 92,
					"instanceVariables": {},
					"behaviors": {},
					"world": {
						"x": 240,
						"y": 0,
						"width": 20,
						"height": 20,
						"originX": 0,
						"originY": 0,
						"color": [
							1,
							1,
							1,
							1
						],
						"angle": 0,
						"zElevation": 0
					}
				},
				{
					"type": "LevelWarp",
					"properties": {
						"initially-visible": false,
						"initial-animation": "Animation 1",
						"initial-frame": 0,
						"enable-collisions": true,
						"live-preview": false
					},
					"uid": 124,
					"instanceVariables": {
						"destination": "Camp_Entry",
						"destX": 220,
						"destY": 40
					},
					"behaviors": {},
					"world": {
						"x": 160,
						"y": 220,
						"width": 20,
						"height": 20,
						"originX": 0,
						"originY": 0,
						"color": [
							1,
							1,
							1,
							1
						],
						"angle": 0,
						"zElevation": 0
					}
				},
				{
					"type": "LevelWarp",
					"properties": {
						"initially-visible": false,
						"initial-animation": "Animation 1",
						"initial-frame": 0,
						"enable-collisions": true,
						"live-preview": false
					},
					"uid": 125,
					"instanceVariables": {
						"destination": "D1_Start",
						"destX": 140,
						"destY": 200
					},
					"behaviors": {},
					"world": {
						"x": 140,
						"y": 0,
						"width": 20,
						"height": 20,
						"originX": 0,
						"originY": 0,
						"color": [
							1,
							1,
							1,
							1
						],
						"angle": 0,
						"zElevation": 0
					}
				},
				{
					"type": "LevelWarp",
					"properties": {
						"initially-visible": false,
						"initial-animation": "Animation 1",
						"initial-frame": 0,
						"enable-collisions": true,
						"live-preview": false
					},
					"uid": 126,
					"instanceVariables": {
						"destination": "D1_Start",
						"destX": 160,
						"destY": 200
					},
					"behaviors": {},
					"world": {
						"x": 160,
						"y": 0,
						"width": 20,
						"height": 20,
						"originX": 0,
						"originY": 0,
						"color": [
							1,
							1,
							1,
							1
						],
						"angle": 0,
						"zElevation": 0
					}
				},
				{
					"type": "LevelWarp",
					"properties": {
						"initially-visible": false,
						"initial-animation": "Animation 1",
						"initial-frame": 0,
						"enable-collisions": true,
						"live-preview": false
					},
					"uid": 127,
					"instanceVariables": {
						"destination": "D1_Start",
						"destX": 180,
						"destY": 200
					},
					"behaviors": {},
					"world": {
						"x": 180,
						"y": 0,
						"width": 20,
						"height": 20,
						"originX": 0,
						"originY": 0,
						"color": [
							1,
							1,
							1,
							1
						],
						"angle": 0,
						"zElevation": 0
					}
				}
			],
			"sid": 654243980274079,
			"effectTypes": [],
			"isInitiallyVisible": true,
			"color": [
				1,
				1,
				1,
				1
			],
			"backgroundColor": [
				0.29411764705882354,
				0.23529411764705882,
				0.29411764705882354,
				1
			],
			"isTransparent": false,
			"parallaxX": 1,
			"parallaxY": 1,
			"scaleRate": 1,
			"forceOwnTexture": false,
			"useRenderCells": false,
			"blendMode": "normal",
			"global": false
		},
		{
			"name": "Collisions",
			"overriden": 0,
			"instances": [
				{
					"type": "Collisions",
					"properties": {
						"initially-visible": false,
						"tile-width": 20,
						"tile-height": 20,
						"tile-x-offset": 0,
						"tile-y-offset": 0,
						"tile-x-spacing": 0,
						"tile-y-spacing": 0,
						"tile-x-drawing-offset": 0,
						"tile-y-drawing-offset": 0,
						"drawing-mode": "top-to-right"
					},
					"uid": 225,
					"instanceVariables": {},
					"behaviors": {},
					"ownData": {
						"tilemapData": {
							"width": 19,
							"height": 14,
							"max-width": 57,
							"max-height": 29,
							"data": "6x0,2x1,22x0,5x1,2x1h,5x1,17x0,1,10x0,1,17x0,1,10x0,1,17x0,1,10x0,1,17x0,1,10x0,1,17x0,1,10x0,1,17x0,1,10x0,1,16x0,1,11x0,1h,1,15x0,1,12x0,1,15x0,1,11x0,1h,1,16x0,1,10x0,1,17x0,1,10x0,1,17x0,1,10x0,1,17x0,1,10x0,1,17x0,1,10x0,1,17x0,1,10x0,1,17x0,12x1,22x0,2x1,81x0,1,1041x0"
						},
						"tile-width": 20,
						"tile-height": 20,
						"tile-x-offset": 0,
						"tile-y-offset": 0,
						"tile-x-spacing": 0,
						"tile-y-spacing": 0
					},
					"world": {
						"x": -20,
						"y": -20,
						"width": 380,
						"height": 280,
						"originX": 0,
						"originY": 0,
						"color": [
							1,
							1,
							1,
							1
						],
						"zElevation": 0
					}
				}
			],
			"sid": 437143821567978,
			"effectTypes": [],
			"isInitiallyVisible": true,
			"color": [
				1,
				1,
				1,
				1
			],
			"backgroundColor": [
				0.3686274509803922,
				0.3686274509803922,
				0.3686274509803922,
				1
			],
			"isTransparent": true,
			"parallaxX": 1,
			"parallaxY": 1,
			"scaleRate": 1,
			"forceOwnTexture": false,
			"useRenderCells": false,
			"blendMode": "normal",
			"global": false
		},
		{
			"name": "Objects",
			"overriden": 0,
			"instances": [
				{
					"type": "LOS",
					"properties": {
						"initially-visible": false,
						"initial-animation": "Animation 1",
						"initial-frame": 0,
						"enable-collisions": true,
						"live-preview": false
					},
					"uid": 234,
					"instanceVariables": {},
					"behaviors": {
						"LineOfSight": {
							"properties": {
								"obstacles": "custom",
								"range": 2000,
								"cone-of-view": 360,
								"use-collision-cells": false
							}
						}
					},
					"world": {
						"x": -40,
						"y": -20,
						"width": 20,
						"height": 20,
						"originX": 0,
						"originY": 0,
						"color": [
							1,
							1,
							1,
							1
						],
						"angle": 0,
						"zElevation": 0
					}
				}
			],
			"sid": 941360700417115,
			"effectTypes": [],
			"isInitiallyVisible": true,
			"color": [
				1,
				1,
				1,
				1
			],
			"backgroundColor": [
				0.3686274509803922,
				0.3686274509803922,
				0.3686274509803922,
				1
			],
			"isTransparent": true,
			"parallaxX": 1,
			"parallaxY": 1,
			"scaleRate": 1,
			"forceOwnTexture": false,
			"useRenderCells": false,
			"blendMode": "normal",
			"global": false
		},
		{
			"name": "Effects",
			"overriden": 0,
			"instances": [],
			"sid": 756179985368649,
			"effectTypes": [],
			"isInitiallyVisible": true,
			"color": [
				1,
				1,
				1,
				1
			],
			"backgroundColor": [
				0.3686274509803922,
				0.3686274509803922,
				0.3686274509803922,
				1
			],
			"isTransparent": true,
			"parallaxX": 1,
			"parallaxY": 1,
			"scaleRate": 1,
			"forceOwnTexture": false,
			"useRenderCells": false,
			"blendMode": "normal",
			"global": false
		},
		{
			"name": "UI",
			"overriden": 0,
			"instances": [
				{
					"type": "TXTerrors",
					"properties": {
						"text": "Err:",
						"enable-bbcode": true,
						"font": "Arial",
						"size": 8,
						"line-height": 0,
						"bold": false,
						"italic": false,
						"color": [
							0,
							0,
							0,
							1
						],
						"horizontal-alignment": "left",
						"vertical-alignment": "top",
						"wrapping": "word",
						"initially-visible": false,
						"origin": "top-left"
					},
					"uid": 246,
					"instanceVariables": {},
					"behaviors": {},
					"world": {
						"x": 0,
						"y": 0,
						"width": 340,
						"height": 20,
						"originX": 0,
						"originY": 0,
						"color": [
							1,
							1,
							1,
							1
						],
						"angle": 0,
						"zElevation": 0
					}
				}
			],
			"sid": 456227960046862,
			"effectTypes": [],
			"isInitiallyVisible": true,
			"color": [
				1,
				1,
				1,
				1
			],
			"backgroundColor": [
				0.3686274509803922,
				0.3686274509803922,
				0.3686274509803922,
				1
			],
			"isTransparent": true,
			"parallaxX": 1,
			"parallaxY": 1,
			"scaleRate": 1,
			"forceOwnTexture": false,
			"useRenderCells": false,
			"blendMode": "normal",
			"global": false
		}
	],
	"sid": 431982549737213,
	"nonworld-instances": [],
	"effectTypes": [],
	"width": 427,
	"height": 240,
	"unboundedScrolling": false,
	"eventSheet": "eGame"
}