{
	"name": "E_GhostParticle",
	"plugin-id": "Sprite",
	"sid": 678312059153611,
	"isGlobal": false,
	"instanceVariables": [],
	"behaviorTypes": [],
	"effectTypes": [],
	"animations": {
		"items": [
			{
				"frames": [
					{
						"width": 20,
						"height": 20,
						"originX": 0.5,
						"originY": 0.5,
						"originalSource": "",
						"exportFormat": "png",
						"exportQuality": 0.8,
						"imageSpriteId": 8594904,
						"useCollisionPoly": true,
						"duration": 1
					},
					{
						"width": 20,
						"height": 20,
						"originX": 0.5,
						"originY": 0.5,
						"originalSource": "",
						"exportFormat": "png",
						"exportQuality": 0.8,
						"imageSpriteId": 3088303,
						"useCollisionPoly": true,
						"duration": 1
					},
					{
						"width": 20,
						"height": 20,
						"originX": 0.5,
						"originY": 0.5,
						"originalSource": "",
						"exportFormat": "png",
						"exportQuality": 0.8,
						"imageSpriteId": 6083524,
						"useCollisionPoly": true,
						"duration": 1
					},
					{
						"width": 20,
						"height": 20,
						"originX": 0.5,
						"originY": 0.5,
						"originalSource": "",
						"exportFormat": "png",
						"exportQuality": 0.8,
						"imageSpriteId": 8508869,
						"useCollisionPoly": true,
						"duration": 1
					},
					{
						"width": 20,
						"height": 20,
						"originX": 0.5,
						"originY": 0.5,
						"originalSource": "",
						"exportFormat": "png",
						"exportQuality": 0.8,
						"imageSpriteId": 3100003,
						"useCollisionPoly": true,
						"duration": 1
					}
				],
				"sid": 609148975458472,
				"name": "Animation 1",
				"isLooping": false,
				"isPingPong": false,
				"repeatCount": 1,
				"repeatTo": 0,
				"speed": 16
			}
		],
		"subfolders": []
	}
}